ok_zadanie_1/__init__.py
ok_zadanie_1/edge/__init__.py
ok_zadanie_1/edge/directed_edge.py
ok_zadanie_1/edge/edge.py
ok_zadanie_1/edge/undirected_edge.py
ok_zadanie_1/graph/__init__.py
ok_zadanie_1/graph/abstract_graph.py
ok_zadanie_1/graph/directed_graph.py
ok_zadanie_1/graph/graph.py
ok_zadanie_1/graph/undirected_graph.py
ok_zadanie_1/graph_creator/__init__.py
ok_zadanie_1/graph_creator/graph_creator.py
ok_zadanie_1/graph_utils/__init__.py
ok_zadanie_1/graph_utils/vertex_degree.py
ok_zadanie_1/graph_visualizer/__init__.py
ok_zadanie_1/vertex/__init__.py
ok_zadanie_1/vertex/vertex.py
ok_zadanie_1-0.0.0.dist-info/WHEEL
ok_zadanie_1-0.0.0.dist-info/METADATA
ok_zadanie_1-0.0.0.dist-info/RECORD
