Metadata-Version: 2.1
Name: ok-zadanie-1
Version: 0.0.0
Summary: 
License: UNLICENSED
Author: Rafał Majewski
Author-email: goodheropl@gmail.com
Requires-Python: >=3.10,<4.0
Classifier: License :: Other/Proprietary License
Classifier: Programming Language :: Python :: 3
Classifier: Programming Language :: Python :: 3.10
Requires-Dist: matplotlib (>=3.6.1,<4.0.0)
Requires-Dist: networkx (>=2.8.7,<3.0.0)
